{
  "window_days": 14,
  "window": {
    "from": "2026-06-11",
    "to": "2026-06-25"
  },
  "bat": {
    "avg": {
      "mean": 0.2582,
      "std": 0.0721
    },
    "obp": {
      "mean": 0.3296,
      "std": 0.0759
    },
    "slg": {
      "mean": 0.4423,
      "std": 0.143
    },
    "hr": {
      "mean": 1.6898,
      "std": 1.3679
    },
    "r": {
      "mean": 5.6776,
      "std": 2.686
    },
    "rbi": {
      "mean": 5.4694,
      "std": 3.1122
    },
    "sb": {
      "mean": 0.7837,
      "std": 1.2446
    },
    "so": {
      "mean": 9.4245,
      "std": 4.2704
    }
  },
  "sp": {
    "era": {
      "mean": 4.5029,
      "std": 3.113
    },
    "whip": {
      "mean": 1.3218,
      "std": 0.4554
    },
    "hr": {
      "mean": 1.7286,
      "std": 1.3982
    },
    "so": {
      "mean": 11.6643,
      "std": 5.0704
    },
    "w": {
      "mean": 0.7571,
      "std": 0.7452
    },
    "qs": {
      "mean": 0.8714,
      "std": 0.7731
    }
  },
  "rp": {
    "era": {
      "mean": 4.0133,
      "std": 4.1001
    },
    "whip": {
      "mean": 1.3194,
      "std": 0.6406
    },
    "hr": {
      "mean": 0.6776,
      "std": 0.8774
    },
    "so": {
      "mean": 5.1262,
      "std": 2.751
    },
    "sv": {
      "mean": 0.4579,
      "std": 1.0073
    },
    "hld": {
      "mean": 0.8411,
      "std": 1.029
    }
  }
}